janis_assistant/__init__.py
janis_assistant/__meta__.py
janis_assistant/cli.py
janis_assistant/main.py
janis_assistant/containers/__init__.py
janis_assistant/containers/base.py
janis_assistant/containers/docker.py
janis_assistant/containers/singularity.py
janis_assistant/data/__init__.py
janis_assistant/data/dbproviderbase.py
janis_assistant/data/keyvaluedbproviderbase.py
janis_assistant/data/container/__init__.py
janis_assistant/data/container/info.py
janis_assistant/data/container/parse_pattern.py
janis_assistant/data/container/registries.py
janis_assistant/data/enums/__init__.py
janis_assistant/data/enums/dbtype.py
janis_assistant/data/enums/taskprogress.py
janis_assistant/data/enums/taskstatus.py
janis_assistant/data/models/__init__.py
janis_assistant/data/models/base.py
janis_assistant/data/models/filescheme.py
janis_assistant/data/models/inputs.py
janis_assistant/data/models/joblabel.py
janis_assistant/data/models/outputs.py
janis_assistant/data/models/preparedjob.py
janis_assistant/data/models/run.py
janis_assistant/data/models/util.py
janis_assistant/data/models/workflowjob.py
janis_assistant/data/providers/__init__.py
janis_assistant/data/providers/inputsdbprovider.py
janis_assistant/data/providers/internalprogressdb.py
janis_assistant/data/providers/janisdbprovider.py
janis_assistant/data/providers/jobdbprovider.py
janis_assistant/data/providers/joblabeldbprovider.py
janis_assistant/data/providers/outputdbprovider.py
janis_assistant/data/providers/rundbprovider.py
janis_assistant/data/providers/submissiondbprovider.py
janis_assistant/data/providers/workflowmetadataprovider.py
janis_assistant/engines/__init__.py
janis_assistant/engines/engine.py
janis_assistant/engines/enginetypes.py
janis_assistant/engines/cromwell/__init__.py
janis_assistant/engines/cromwell/cromwellconfiguration.py
janis_assistant/engines/cromwell/cromwellmetadata.py
janis_assistant/engines/cromwell/data_types.py
janis_assistant/engines/cromwell/main.py
janis_pipelines.runner-0.13.0.dist-info/LICENSE
janis_pipelines.runner-0.13.0.dist-info/METADATA
janis_pipelines.runner-0.13.0.dist-info/WHEEL
janis_pipelines.runner-0.13.0.dist-info/entry_points.txt
janis_pipelines.runner-0.13.0.dist-info/top_level.txt
janis_pipelines.runner-0.13.0.dist-info/RECORD
