Metadata-Version: 2.1
Name: janis-pipelines.runner
Version: 0.13.0
Summary: Easier way to run workflows, configurable across environments
Author-email: Michael Franklin <michael.franklin@petermac.org>, Grace Hall <grace.hall1@unimelb.edu.au>, Richard Lupat <Richard.Lupat@petermac.org>, Evan Thomas <thomas.e@wehi.edu.au>
Maintainer-email: Grace Hall <grace.hall1@unimelb.edu.au>, Richard Lupat <Richard.Lupat@petermac.org>
License: GNU GENERAL PUBLIC LICENSE
Project-URL: repository, https://github.com/PMCC-BioinformaticsCore/janis-assistant
Project-URL: documentation, https://janis.readthedocs.io/en/latest/
Keywords: janis,workflows,assistant
Classifier: Development Status :: 4 - Beta
Classifier: Environment :: Console
Classifier: Intended Audience :: Developers
Classifier: Intended Audience :: Science/Research
Classifier: Topic :: Scientific/Engineering
Requires-Python: >=3.10.5
License-File: LICENSE
Requires-Dist: janis-pipelines.core
Requires-Dist: janis-pipelines.bioinformatics
Requires-Dist: janis-pipelines.unix
Requires-Dist: janis-pipelines.templates (>=0.11.0)
Requires-Dist: ruamel.yaml (<=0.16.5,>=0.12.4)
Requires-Dist: progressbar2
Requires-Dist: path
Requires-Dist: black
Requires-Dist: pre-commit
Requires-Dist: requests
Requires-Dist: python-dateutil
Requires-Dist: tabulate
Requires-Dist: cwltool
Requires-Dist: cwl-utils (==0.15)
Requires-Dist: blessed
Requires-Dist: regex
Provides-Extra: ci
Requires-Dist: codecov ; extra == 'ci'
Requires-Dist: coverage ; extra == 'ci'
Requires-Dist: requests-mock ; extra == 'ci'
Requires-Dist: nose-parameterized ; extra == 'ci'
Requires-Dist: keyring (==21.4.0) ; extra == 'ci'
Requires-Dist: setuptools (>=67.8.0) ; extra == 'ci'
Requires-Dist: wheel ; extra == 'ci'
Requires-Dist: twine ; extra == 'ci'
Provides-Extra: gcs
Requires-Dist: google-cloud-storage ; extra == 'gcs'
